monitoro/__init__.py
monitoro/client.py
monitoro/exceptions.py
monitoro-0.2.3.dist-info/METADATA
monitoro-0.2.3.dist-info/WHEEL
monitoro-0.2.3.dist-info/top_level.txt
monitoro-0.2.3.dist-info/RECORD
