Metadata-Version: 2.1
Name: monitoro
Version: 0.2.3
Summary: Official Python SDK for the Monitoro API
Home-page: https://github.com/monitoro-inc/python-client
Author: Omar Kamali
Author-email: support@monitoro.co
Keywords: monitoro,scraping,web scraping,web scraping api,local scraping,generative AI,agent tools
Classifier: Development Status :: 3 - Alpha
Classifier: Intended Audience :: Developers
Classifier: License :: OSI Approved :: MIT License
Classifier: Operating System :: OS Independent
Classifier: Programming Language :: Python :: 3
Classifier: Programming Language :: Python :: 3.6
Classifier: Programming Language :: Python :: 3.7
Classifier: Programming Language :: Python :: 3.8
Classifier: Programming Language :: Python :: 3.9
Classifier: Programming Language :: Python :: 3.10
Classifier: Programming Language :: Python :: 3.11
Requires-Python: >=3.6
Requires-Dist: requests>=2.25.1
Requires-Dist: tqdm>=4.60.0
